Metadata-Version: 2.2
Name: gaussian-viewer
Version: 0.1.0
Summary: A lightweight WebGL-based viewer for 3D Gaussian Splatting models
Home-page: https://github.com/LiXin97/gaussian-viewer
Author: Xin Li
Author-email: lixin.1997.lixin@gmail.com
Classifier: Development Status :: 3 - Alpha
Classifier: Intended Audience :: Science/Research
Classifier: License :: OSI Approved :: MIT License
Classifier: Programming Language :: Python :: 3
Classifier: Programming Language :: Python :: 3.8
Classifier: Programming Language :: Python :: 3.9
Classifier: Programming Language :: Python :: 3.10
Classifier: Topic :: Scientific/Engineering :: Visualization
Requires-Python: >=3.8
Requires-Dist: aiohttp
Requires-Dist: websockets
Requires-Dist: numpy
Requires-Dist: plyfile
Dynamic: author
Dynamic: author-email
Dynamic: classifier
Dynamic: description
Dynamic: description-content-type
Dynamic: home-page
Dynamic: requires-dist
Dynamic: requires-python
Dynamic: summary
